pyranker/__init__.py
pyranker/preprocessing/__init__.py
pyranker/preprocessing/normalizer.py
pyranker/preprocessing/tokenizer.py
pyranker/rankers/__init__.py
pyranker/rankers/bm25.py
pyranker/rankers/tf_idf.py
pyranker/rankers/vspace.py
pyranker-0.1.3.dist-info/LICENSE
pyranker-0.1.3.dist-info/METADATA
pyranker-0.1.3.dist-info/WHEEL
pyranker-0.1.3.dist-info/top_level.txt
pyranker-0.1.3.dist-info/RECORD
